nine/__init__.py
nine/decorator.py
nine/test_nine.py
nine-1.2.0.dist-info/LICENSE.rst
nine-1.2.0.dist-info/METADATA
nine-1.2.0.dist-info/WHEEL
nine-1.2.0.dist-info/entry_points.txt
nine-1.2.0.dist-info/RECORD
